data_validator/__init__.py
data_validator/common.py
data_validator/constraints.py
data_validator/customexceptions/__init__.py
data_validator/customexceptions/array.py
data_validator/customexceptions/common.py
data_validator/customexceptions/integer.py
data_validator/customexceptions/string.py
data_validator/datacheckers/__init__.py
data_validator/datacheckers/array.py
data_validator/datacheckers/boolean.py
data_validator/datacheckers/dictionary.py
data_validator/datacheckers/float.py
data_validator/datacheckers/integer.py
data_validator/datacheckers/string.py
data_validator/validator.py
json_data_validator-0.1.0.dist-info/METADATA
json_data_validator-0.1.0.dist-info/WHEEL
json_data_validator-0.1.0.dist-info/RECORD
