Metadata-Version: 2.1
Name: json-data-validator
Version: 0.1.0
Summary: 
Author: Smolke
Author-email: d.smolczynski1@gmail.com
Requires-Python: >=3.11,<4.0
Classifier: Programming Language :: Python :: 3
Classifier: Programming Language :: Python :: 3.11
